icu4py/__init__.py
icu4py/_version.cpp
icu4py/_version.cpython-313t-i386-linux-gnu.so
icu4py/_version.pyi
icu4py/locale.cpp
icu4py/locale.cpython-313t-i386-linux-gnu.so
icu4py/locale.pyi
icu4py/messageformat.cpp
icu4py/messageformat.cpython-313t-i386-linux-gnu.so
icu4py/messageformat.pyi
icu4py/py.typed
icu4py.libs/libicudata-6b8dd726.so.60.3
icu4py.libs/libicui18n-b2c40b87.so.60.3
icu4py.libs/libicuuc-0090835d.so.60.3
icu4py-0.2.0.dist-info/METADATA
icu4py-0.2.0.dist-info/WHEEL
icu4py-0.2.0.dist-info/top_level.txt
icu4py-0.2.0.dist-info/RECORD
icu4py-0.2.0.dist-info/licenses/LICENSE
icu4py-0.2.0.dist-info/sboms/auditwheel.cdx.json
