Metadata-Version: 2.4
Name: icu4py
Version: 0.2.0
Summary: Bindings to the ICU (International Components for Unicode) library (ICU4C).
Author-email: Adam Johnson <me@adamj.eu>
License-Expression: MIT
Project-URL: Changelog, https://icu4py.readthedocs.io/en/latest/changelog.html
Project-URL: Documentation, https://icu4py.readthedocs.io/
Project-URL: Funding, https://adamj.eu/books/
Project-URL: Repository, https://github.com/adamchainz/icu4py
Keywords: i18n,icu,icu4c,internationalization,l10n,localization,unicode
Classifier: Development Status :: 5 - Production/Stable
Classifier: Framework :: Pytest
Classifier: Intended Audience :: Developers
Classifier: Natural Language :: English
Classifier: Operating System :: OS Independent
Classifier: Programming Language :: Python :: 3 :: Only
Classifier: Programming Language :: Python :: 3.10
Classifier: Programming Language :: Python :: 3.11
Classifier: Programming Language :: Python :: 3.12
Classifier: Programming Language :: Python :: 3.13
Classifier: Programming Language :: Python :: 3.14
Classifier: Typing :: Typed
Requires-Python: >=3.10
License-File: LICENSE
Requires-Dist: typing-extensions>=4.15
Dynamic: license-file
